ttn_client/__init__.py
ttn_client/client.py
ttn_client/const.py
ttn_client/py.typed
ttn_client/exceptions/__init__.py
ttn_client/exceptions/auth_error.py
ttn_client/parsers/__init__.py
ttn_client/parsers/default.py
ttn_client/parsers/sensecap.py
ttn_client/values/__init__.py
ttn_client/values/base.py
ttn_client/values/binary_sensor.py
ttn_client/values/device_tracker.py
ttn_client/values/sensor.py
ttn_client-1.2.2.dist-info/METADATA
ttn_client-1.2.2.dist-info/WHEEL
ttn_client-1.2.2.dist-info/licenses/LICENSE
ttn_client-1.2.2.dist-info/RECORD
